yolo_auto/__init__.py
yolo_auto/yolov3auto.py
yolo_auto-0.0.2.dist-info/LICENSE
yolo_auto-0.0.2.dist-info/METADATA
yolo_auto-0.0.2.dist-info/WHEEL
yolo_auto-0.0.2.dist-info/top_level.txt
yolo_auto-0.0.2.dist-info/RECORD
