Metadata-Version: 2.1
Name: yolo-auto
Version: 0.0.2
Summary: Train custom YOLOv3 object detectors in two lines
Home-page: https://github.com/pandeajrun242
Author: Arjun Pandey
Author-email: apandey@jpischool.com
License: UNKNOWN
Platform: UNKNOWN
Classifier: Programming Language :: Python :: 3
Classifier: License :: OSI Approved :: MIT License
Classifier: Operating System :: OS Independent
Requires-Python: >=3.6
Requires-Dist: GitPython
